{
  "R.E.P.O.": [
    {
      "date": "2026-05-28",
      "ccu": 40801,
      "positive_rate": 92.9,
      "total_reviews": 14368
    },
    {
      "date": "2026-06-01",
      "ccu": 41696,
      "positive_rate": 92.9,
      "total_reviews": 14450
    }
  ],
  "Lethal Company": [
    {
      "date": "2026-05-28",
      "ccu": 5612,
      "positive_rate": 93.0,
      "total_reviews": 17577
    },
    {
      "date": "2026-06-01",
      "ccu": 5736,
      "positive_rate": 93.0,
      "total_reviews": 17591
    }
  ],
  "Phasmophobia": [
    {
      "date": "2026-05-28",
      "ccu": 10527,
      "positive_rate": 90.7,
      "total_reviews": 26671
    },
    {
      "date": "2026-06-01",
      "ccu": 11313,
      "positive_rate": 90.7,
      "total_reviews": 26701
    }
  ],
  "Content Warning": [
    {
      "date": "2026-05-28",
      "ccu": 1094,
      "positive_rate": 89.9,
      "total_reviews": 6814
    },
    {
      "date": "2026-06-01",
      "ccu": 1371,
      "positive_rate": 89.9,
      "total_reviews": 6820
    }
  ],
  "FEEDERS": [
    {
      "date": "2026-05-28",
      "ccu": 0,
      "positive_rate": 0.0,
      "total_reviews": 0
    },
    {
      "date": "2026-06-01",
      "ccu": 0,
      "positive_rate": 0.0,
      "total_reviews": 0
    }
  ],
  "NARAKA: BLADEPOINT": [
    {
      "date": "2026-06-01",
      "ccu": 12987,
      "positive_rate": 72.0,
      "total_reviews": 250340
    }
  ]
}